userscloud/__init__.py
userscloud/api.py
userscloud/ftp.py
userscloud/helper.py
userscloud/utils.py
userscloud/web.py
userscloud/__metadata__/DISCLIAIMER.md
userscloud/__metadata__/LICENSE
userscloud/__metadata__/README.md
userscloud/__metadata__/__init__.py
userscloud/__metadata__/requirements.txt
userscloud/__metadata__/requirements_extra.json
userscloud-0.1.0.dist-info/METADATA
userscloud-0.1.0.dist-info/WHEEL
userscloud-0.1.0.dist-info/top_level.txt
userscloud-0.1.0.dist-info/RECORD
