Metadata-Version: 2.1
Name: userscloud
Version: 0.1.0
Summary: userscloud complete API including web frontend, HTTP and FTP.
Home-page: http://code.foxe6.kozow.com/userscloud/
Author: f̣ộx̣ệ6
Author-email: foxe6@pm.me
License: AGPL-3.0
Project-URL: Sourcecode, http://code.foxe6.kozow.com/userscloud.zip
Project-URL: Documentation, http://code.foxe6.kozow.com/userscloud/docs/
Project-URL: Example, http://code.foxe6.kozow.com/userscloud/test/
Project-URL: Funding, https://paypal.me/foxe6
Project-URL: Say Thanks!, https://saythanks.io/to/foxe6
Keywords: userscloud file host ftp batch remote upload api cli manager archive
Platform: UNKNOWN
Classifier: Programming Language :: Python :: 3.9
Classifier: Topic :: Utilities
Classifier: Natural Language :: English
Classifier: Intended Audience :: Developers
Classifier: License :: OSI Approved :: GNU Affero General Public License v3
Classifier: Operating System :: MacOS
Classifier: Operating System :: POSIX
Classifier: Operating System :: Microsoft :: Windows :: Windows 10
Classifier: Development Status :: 5 - Production/Stable
Requires-Python: >=3.5
Requires-Dist: lxml (>=0.0.1)
Requires-Dist: requests (>=0.0.1)
Requires-Dist: requests-toolbelt (>=0.0.1)
Requires-Dist: sqlq (>=0.0.1)
Requires-Dist: omnitools (>=0.0.1)
Requires-Dist: aescipher (>=0.0.1)
Requires-Dist: easyrsa (>=0.0.1)
Requires-Dist: credsafe (>=0.0.1)
Provides-Extra: efc
Requires-Dist: ucefc ; extra == 'efc'
Requires-Dist: ucefcdownloader ; extra == 'efc'
Requires-Dist: ucefcuploader ; extra == 'efc'
